beatrica_embedding/__init__.py
beatrica_embedding/embedding_generator.py
beatrica_embedding-2025.5.180922.dist-info/licenses/LICENSE
tests/__init__.py
tests/test_embedding_generator.py
beatrica_embedding-2025.5.180922.dist-info/METADATA
beatrica_embedding-2025.5.180922.dist-info/WHEEL
beatrica_embedding-2025.5.180922.dist-info/top_level.txt
beatrica_embedding-2025.5.180922.dist-info/RECORD
